django_readers_debug/__init__.py
django_readers_debug-0.0.4.dist-info/LICENSE
django_readers_debug-0.0.4.dist-info/METADATA
django_readers_debug-0.0.4.dist-info/WHEEL
django_readers_debug-0.0.4.dist-info/top_level.txt
django_readers_debug-0.0.4.dist-info/RECORD
