Metadata-Version: 2.1
Name: django-readers-debug
Version: 0.0.4
Summary: A pretty-printer for debugging django-readers queryset functions
Home-page: https://github.com/dabapps/django-readers-debug
Author: DabApps
Author-email: hello@dabapps.com
License: BSD
Project-URL: Changelog, https://github.com/dabapps/django-readers-debug/releases
Project-URL: Issues, https://github.com/dabapps/django-readers-debug/issues
Platform: UNKNOWN
Requires-Python: >=3.6
Requires-Dist: black
Requires-Dist: django-readers
